CHANGELOG.txt
LICENSE.txt
MANIFEST.in
README.txt
setup.py
markupFor3DSlicer/__init__.py
markupFor3DSlicer.egg-info/PKG-INFO
markupFor3DSlicer.egg-info/SOURCES.txt
markupFor3DSlicer.egg-info/dependency_links.txt
markupFor3DSlicer.egg-info/top_level.txt