Metadata-Version: 1.1
Name: markupFor3DSlicer
Version: 0.1
Summary: Librairie de création de Markup pour 3D SLicer.
Home-page: UNKNOWN
Author: Guillaume ROCHE
Author-email: g.roche1712@protonmail.com
License: MIT
Keywords: markup
Platform: UNKNOWN
Classifier: Development Status :: 5 - Production/Stable
Classifier: Intended Audience :: Education
Classifier: Operating System :: Microsoft :: Windows :: Windows 10
Classifier: License :: OSI Approved :: MIT License
Classifier: Programming Language :: Python :: 3
